inireader/__init__.py
inireader-0.2.0.dist-info/METADATA
inireader-0.2.0.dist-info/WHEEL
inireader-0.2.0.dist-info/top_level.txt
inireader-0.2.0.dist-info/RECORD
