Metadata-Version: 2.1
Name: inireader
Version: 0.2.0
Summary: ini file reader
Home-page: https://hg.sr.ht/~pythonian/inireader
Author: Aurélien Campéas
Author-email: aurelien.campeas@pythonian.fr
License: UNKNOWN
Platform: UNKNOWN
